setup.cfg
setup.py
fbrecog/__init__.py
fbrecog.egg-info/PKG-INFO
fbrecog.egg-info/SOURCES.txt
fbrecog.egg-info/dependency_links.txt
fbrecog.egg-info/not-zip-safe
fbrecog.egg-info/requires.txt
fbrecog.egg-info/top_level.txt