Metadata-Version: 1.0
Name: fbrecog
Version: 1.4
Summary: An unoffcial wrapper for Facebook's recognition endpoint
Home-page: http://github.com/samj1912/fbrecog
Author: Sambhav Kothari
Author-email: sambhavs.email@gmail.com
License: MIT
Platform: UNKNOWN
